{
    "overview": [
        "<p>This subject is offered as one in a series of four subjects for students enrolled in the Postgraduate Diploma in Clinical Dentistry. Students study implant dentistry, oral medicine or oral surgery. For further information about the implant dentistry content, please contact Dr Roy Judge. For further information about he oral medicine content, please contact Associate Professor Michael McCullough. For further information about the oral surgery content, please contact Associate Professor Andrew Smith. Please see the web link above for further details.</p>"
    ],
    "ilo": [
        "Semester 2Principal coordinatorDavid MantonMode of deliveryOn Campus (Parkville)Contact hoursIMPLANT DENTISTRY - The group entering 2009 will have alternative Monday afternoons on the surgical clinic, Tuesday morning will be research, Tuesday and Wednesday afternoon will be the restorative clinics. Typically the students will attend one surgical and one restorative clinic per week. Students will have 36 weeks of contact per year over two years. ORAL MEDICINE - Please contact Associate Professor Michael McCullough for details. ORAL SURGERY - Please contact Associate Professor Andrew Smith for details.Teaching period22 July 2024 to 20 October 2024Last self-enrol date2 August 2024Census date2 September 2024Last date to withdraw without fail20 September 2024Assessment period ends15 November 2024Semester 2 contact informationMelbourne Dental SchoolSpecialist CoordinatorImplants - Dr Jaafar AbduoCurrently enrolled students:General information:https://ask.unimelb.edu.auEmail:enquiries-STEM@unimelb.edu.au",
        "General information:https://ask.unimelb.edu.au",
        "Email:enquiries-STEM@unimelb.edu.au"
    ],
    "elig_req": {
        "Prerequisites": [],
        "Corequisites": [],
        "Non-allowed subjects": [],
        "Inherent requirements (core participation requirements)": [
            {
                "type": "paragraph",
                "content": "Further details on how to seek academic adjustments can be found on the Student Equity and Disability Support website:http://services.unimelb.edu.au/student-equity/home"
            }
        ]
    },
    "assessment": [
        {
            "brief": "IMPLANT DENTISTRY: On going clinical assesment on the restorative and surgical clinics will occur throughout the two years. The prepared seminars in each clinic stream will be assessed and feedback directly provided. At the end of year one a mock viva will be conducted allowing the students to gauge their effectiveness in learning. At the end of two years the exit exam will be a restorative/surgical viva as well as a combined 3 hour paper.",
            "bullets": null,
            "hurdle": null,
            "timing": "Throughout the teaching period",
            "percentage": "N/A"
        },
        {
            "brief": "ORAL SURGERY: Please contact Associate Professor Andrew Smith for details of assessment for students taking oral surgery.",
            "bullets": null,
            "hurdle": null,
            "timing": "Throughout the teaching period",
            "percentage": "N/A"
        },
        {
            "brief": "ORAL MEDICINE: Please contact Associate Professor Michael McCullough for details of assessment for students taking oral medicine.",
            "bullets": null,
            "hurdle": null,
            "timing": "Throughout the teaching period",
            "percentage": "N/A"
        }
    ],
    "date_times": [
        {
            "semester": "Semester 2",
            "principal_coordinator": "David Manton",
            "mode_of_delivery": "On Campus (Parkville)",
            "contact_hours": "IMPLANT DENTISTRY - The group entering 2009 will have alternative Monday afternoons on the surgical clinic, Tuesday morning will be research, Tuesday and Wednesday afternoon will be the restorative clinics. Typically the students will attend one surgical and one restorative clinic per week. Students will have 36 weeks of contact per year over two years. ORAL MEDICINE - Please contact Associate Professor Michael McCullough for details. ORAL SURGERY - Please contact Associate Professor Andrew Smith for details.",
            "total_time_commitment": null,
            "teaching_period": "22 July 2024 to 20 October 2024",
            "last_self_enrol_date": "2 August 2024",
            "census_date": "2 September 2024",
            "last_date_to_withdraw_without_fail": "20 September 2024",
            "assessment_period_ends": "15 November 2024",
            "contact_name": "Currently enrolled students:",
            "contact_email": null
        }
    ]
}