{
    "overview": [
        "<p>This subject, currently subtitled \"Tools for Research, Writing and Publishing\", introduces students to critical analysis of literature, planning a research protocol and writing a thesis.</p>"
    ],
    "ilo": [
        "Semester 1Principal coordinatorDavid MantonMode of deliveryOn Campus (Parkville)Contact hoursOne 1-hour lecture each week plus three hours of non-contact private study each week.Teaching period26 February 2024 to 26 May 2024Last self-enrol date8 March 2024Census date3 April 2024Last date to withdraw without fail3 May 2024Assessment period ends21 June 2024Semester 1 contact informationMelbourne Dental SchoolSpecialist CoordinatorsEndodontics - Professor Peter ParashosOral Medicine - Professor Michael McCulloughOrthodontics - Associate Professor Paul SchneiderPaediatric Dentistry - Professor David MantonPeriodontics - Professor Ivan DarbyProsthodontics - Associate Professor Roy JudgeSpecial Needs Dentistry - Associate Professor Mina BorromeoCurrently enrolled students:General information:https://ask.unimelb.edu.auEmail:enquiries-STEM@unimelb.edu.au",
        "General information:https://ask.unimelb.edu.au",
        "Email:enquiries-STEM@unimelb.edu.au"
    ],
    "elig_req": {
        "Prerequisites": [],
        "Corequisites": [],
        "Non-allowed subjects": [],
        "Inherent requirements (core participation requirements)": [
            {
                "type": "paragraph",
                "content": "Further details on how to seek academic adjustments can be found on the Student Equity and Disability Support website:http://services.unimelb.edu.au/student-equity/home"
            }
        ]
    },
    "assessment": [
        {
            "brief": "Assessment consists of one written assignment. The assignment is open-book in style, and addresses current issues in information collection, critical analysis of current literature and research design.",
            "bullets": null,
            "hurdle": null,
            "timing": "",
            "percentage": "100%"
        }
    ],
    "date_times": [
        {
            "semester": "Semester 1",
            "principal_coordinator": "David Manton",
            "mode_of_delivery": "On Campus (Parkville)",
            "contact_hours": "One 1-hour lecture each week plus three hours of non-contact private study each week.",
            "total_time_commitment": null,
            "teaching_period": "26 February 2024 to 26 May 2024",
            "last_self_enrol_date": "8 March 2024",
            "census_date": "3 April 2024",
            "last_date_to_withdraw_without_fail": "3 May 2024",
            "assessment_period_ends": "21 June 2024",
            "contact_name": "Currently enrolled students:",
            "contact_email": null
        }
    ]
}